{"moduleName":null,"summaries":[{"symbol":{"__symbol":0,"members":[]},"metadata":{"__symbolic":"class","extends":{"__symbol":1,"members":[]},"members":{"billStatus_BillState":[{"__symbolic":"property","decorators":[{"__symbolic":"call","expression":{"__symbol":2,"members":[]},"arguments":[{"id":"billStatus.billState","name":"{{billStatus_BillState_6a6f7e09_pbh3}}","binding":"billStatus.billState","updateOn":"change","defaultI18nValue":"审批状态"}]}]}],"applicant_Applicant_Name":[{"__symbolic":"property","decorators":[{"__symbolic":"call","expression":{"__symbol":2,"members":[]},"arguments":[{"id":"applicant.applicant_Name","name":"{{applicant_Applicant_Name_36e050c8_radi}}","binding":"applicant.applicant_Name","updateOn":"blur","defaultI18nValue":"制单人"}]}]}],"deliveryDate":[{"__symbolic":"property","decorators":[{"__symbolic":"call","expression":{"__symbol":2,"members":[]},"arguments":[{"id":"deliveryDate","name":"{{deliveryDate_19bd9bfb_nnlo}}","binding":"deliveryDate","updateOn":"blur","valueConverter":{"__symbolic":"new","expression":{"__symbol":3,"members":[]},"arguments":["yyyy-MM-dd"]},"defaultI18nValue":"交货日期"}]}]}],"purchaseDept_PurchaseDept_name":[{"__symbolic":"property","decorators":[{"__symbolic":"call","expression":{"__symbol":2,"members":[]},"arguments":[{"id":"purchaseDept.purchaseDept_name","name":"{{purchaseDept_PurchaseDept_name_53265c41_3q8s}}","binding":"purchaseDept.purchaseDept_name","updateOn":"blur","defaultI18nValue":"采购部门"}]}]}],"planCode":[{"__symbolic":"property","decorators":[{"__symbolic":"call","expression":{"__symbol":2,"members":[]},"arguments":[{"id":"planCode","name":"{{planCode_210f7065_7a35}}","binding":"planCode","updateOn":"blur","defaultI18nValue":"计划编号"}]}]}],"planName":[{"__symbolic":"property","decorators":[{"__symbolic":"call","expression":{"__symbol":2,"members":[]},"arguments":[{"id":"planName","name":"{{planName_4f24ebc0_a9kt}}","binding":"planName","updateOn":"blur","defaultI18nValue":"计划名称"}]}]}],"isPurchaseOrder":[{"__symbolic":"property","decorators":[{"__symbolic":"call","expression":{"__symbol":2,"members":[]},"arguments":[{"id":"isPurchaseOrder","name":"{{isPurchaseOrder_75108363_6uu3}}","binding":"isPurchaseOrder","updateOn":"change","defaultI18nValue":"是否已生成采购订单"}]}]}],"totalPrice":[{"__symbolic":"property","decorators":[{"__symbolic":"call","expression":{"__symbol":2,"members":[]},"arguments":[{"id":"totalPrice","name":"{{totalPrice_da36cd69_48ad}}","binding":"totalPrice","updateOn":"blur","defaultI18nValue":"物料总价"}]}]}],"purchaser_Purchaser_Name":[{"__symbolic":"property","decorators":[{"__symbolic":"call","expression":{"__symbol":2,"members":[]},"arguments":[{"id":"purchaser.purchaser_Name","name":"{{purchaser_Purchaser_Name_e646ee4c_5c6k}}","binding":"purchaser.purchaser_Name","updateOn":"blur","defaultI18nValue":"采购员"}]}]}]}},"type":{"summaryKind":3,"type":{"reference":{"__symbol":0,"members":[]},"diDeps":[],"lifecycleHooks":[1]}}}],"symbols":[{"__symbol":0,"name":"DataGridComponentViewmodelForm","filePath":"./datagridcomponentviewmodelform"},{"__symbol":1,"name":"Form","filePath":"@farris/devkit"},{"__symbol":2,"name":"NgFormControl","filePath":"@farris/devkit"},{"__symbol":3,"name":"DateConverter","filePath":"@farris/kendo-binding"}]}